historical_reports/__about__.py
historical_reports/__init__.py
historical_reports/s3/__init__.py
historical_reports/s3/cli.py
historical_reports/s3/config.py
historical_reports/s3/entrypoints.py
historical_reports/s3/generate.py
historical_reports/s3/models.py
historical_reports/s3/update.py
historical_reports/s3/util.py
historical_reports/s3/tests/__init__.py
historical_reports/s3/tests/conftest.py
historical_reports/s3/tests/factories.py
historical_reports/s3/tests/test_everything.py
historical_reports-0.2.0.dist-info/DESCRIPTION.rst
historical_reports-0.2.0.dist-info/METADATA
historical_reports-0.2.0.dist-info/RECORD
historical_reports-0.2.0.dist-info/WHEEL
historical_reports-0.2.0.dist-info/entry_points.txt
historical_reports-0.2.0.dist-info/metadata.json
historical_reports-0.2.0.dist-info/top_level.txt
