Metadata-Version: 2.0
Name: historical-reports
Version: 0.2.0
Summary: Collection of reporting functions built on top of Historical data sets.
Home-page: https://github.com/Netflix-Skunkworks/historical-reports
Author: The Historical developers
Author-email: security@netflix.com
License: UNKNOWN
Keywords: aws,account_management,s3
Platform: UNKNOWN
Requires-Dist: botocore (==1.10.84)
Requires-Dist: historical (>=0.4.1)
Requires-Dist: retrying (==1.3.3)
Requires-Dist: click (==6.7)
Provides-Extra: tests
Requires-Dist: pytest (==3.1.3); extra == 'tests'
Requires-Dist: pytest-cov (>=2.5.1); extra == 'tests'
Requires-Dist: moto (>=1.3.2); extra == 'tests'
Requires-Dist: coveralls (==1.1); extra == 'tests'
Requires-Dist: factory-boy (==2.9.2); extra == 'tests'
Requires-Dist: tox (==2.9.1); extra == 'tests'
